README.md
setup.py
bids_term_to_table.egg-info/PKG-INFO
bids_term_to_table.egg-info/SOURCES.txt
bids_term_to_table.egg-info/dependency_links.txt
bids_term_to_table.egg-info/entry_points.txt
bids_term_to_table.egg-info/requires.txt
bids_term_to_table.egg-info/top_level.txt
bin/bids_term_to_table
utils/__init__.py
utils/add_term.py
utils/bidsterms2pdf.py
utils/github_utils.py
utils/table_utils.py