Metadata-Version: 1.2
Name: bids-term-to-table
Version: 1.0.0
Summary: bids_terms_to_pdf_table: Utilty for creating Markdown table of BIDS terms and adding new BIDS terms 
Home-page: https://github.com/nqueder/bids_terms_to_pdf_table
Author: Nazek Queder, David Keator
Author-email: nqueder@uci.edu, dbkeator@uci.edu
Maintainer: Nazek Queder, David Keator
Maintainer-email: nqueder@uci.edu, dbkeator@uci.edu
License: Apache License 2.0
Platform: UNKNOWN
Classifier: Development Status :: 3 - Alpha
Classifier: Environment :: Console
Classifier: Intended Audience :: Science/Research
Classifier: License :: OSI Approved :: Apache Software License
Classifier: Operating System :: MacOS :: MacOS X
Classifier: Operating System :: POSIX :: Linux
Classifier: Programming Language :: Python :: 3
Classifier: Topic :: Scientific/Engineering
